pash_annotations/__init__.py
pash_annotations/annotation_cli.py
pash_annotations/util.py
pash_annotations/util_flag_option.py
pash_annotations/util_standard.py
pash_annotations/annotation_generation/AnnotationGeneration.py
pash_annotations/annotation_generation/__init__.py
pash_annotations/annotation_generation/annotation_generators/Generator_Interface.py
pash_annotations/annotation_generation/annotation_generators/InputOutputInfoGeneratorAltBigramAuxReduce.py
pash_annotations/annotation_generation/annotation_generators/InputOutputInfoGeneratorAltBigramsAux.py
pash_annotations/annotation_generation/annotation_generators/InputOutputInfoGeneratorAwk.py
pash_annotations/annotation_generation/annotation_generators/InputOutputInfoGeneratorBigramsAux.py
pash_annotations/annotation_generation/annotation_generators/InputOutputInfoGeneratorCat.py
pash_annotations/annotation_generation/annotation_generators/InputOutputInfoGeneratorCol.py
pash_annotations/annotation_generation/annotation_generators/InputOutputInfoGeneratorComm.py
pash_annotations/annotation_generation/annotation_generators/InputOutputInfoGeneratorCustomSort.py
pash_annotations/annotation_generation/annotation_generators/InputOutputInfoGeneratorCustomTr.py
pash_annotations/annotation_generation/annotation_generators/InputOutputInfoGeneratorCut.py
pash_annotations/annotation_generation/annotation_generators/InputOutputInfoGeneratorDiff.py
pash_annotations/annotation_generation/annotation_generators/InputOutputInfoGeneratorGrep.py
pash_annotations/annotation_generation/annotation_generators/InputOutputInfoGeneratorHead.py
pash_annotations/annotation_generation/annotation_generators/InputOutputInfoGeneratorMkfifo.py
pash_annotations/annotation_generation/annotation_generators/InputOutputInfoGeneratorMv.py
pash_annotations/annotation_generation/annotation_generators/InputOutputInfoGeneratorRm.py
pash_annotations/annotation_generation/annotation_generators/InputOutputInfoGeneratorSed.py
pash_annotations-0.2.4.dist-info/LICENSE
pash_annotations-0.2.4.dist-info/METADATA
pash_annotations-0.2.4.dist-info/WHEEL
pash_annotations-0.2.4.dist-info/top_level.txt
pash_annotations-0.2.4.dist-info/RECORD
