Metadata-Version: 2.2
Name: pash-annotations
Version: 0.2.4
Requires-Python: >=3.8
License-File: LICENSE
Dynamic: description
Dynamic: description-content-type
Dynamic: requires-python
